fasta2homozygous.py
fastq2insert_size.py
fastq2mates.py
fastq2sspace.py
filterReads.py
redundans.py
redundans-0.13a5.dist-info/DESCRIPTION.rst
redundans-0.13a5.dist-info/METADATA
redundans-0.13a5.dist-info/RECORD
redundans-0.13a5.dist-info/WHEEL
redundans-0.13a5.dist-info/entry_points.txt
redundans-0.13a5.dist-info/metadata.json
redundans-0.13a5.dist-info/top_level.txt
