Metadata-Version: 2.0
Name: redundans
Version: 0.13a5
Summary: UNKNOWN
Home-page: https://github.com/lpryszcz/redundans
Author: Leszek Pryszcz
Author-email: l.p.pryszcz+distutils@gmail.com
License: GPLv3
Keywords: heterozygous genome assembly scaffolding reduction paired-end long-reads synteny
Platform: UNKNOWN
Classifier: Development Status :: 4 - Beta
Classifier: Programming Language :: Python :: 2
Classifier: Programming Language :: Python :: 2.7
Requires-Dist: FastaIndex
Requires-Dist: pyScaf
